aurelian/__init__.py
aurelian/agents/__init__.py
aurelian/agents/amigo/__init__.py
aurelian/agents/amigo/amigo_agent.py
aurelian/agents/amigo/amigo_config.py
aurelian/agents/amigo/amigo_evals.py
aurelian/agents/amigo/amigo_gradio.py
aurelian/agents/amigo/amigo_mcp.py
aurelian/agents/amigo/amigo_tools.py
aurelian/agents/biblio/__init__.py
aurelian/agents/biblio/biblio_agent.py
aurelian/agents/biblio/biblio_config.py
aurelian/agents/biblio/biblio_gradio.py
aurelian/agents/biblio/biblio_mcp.py
aurelian/agents/biblio/biblio_tools.py
aurelian/agents/biblio_agent.py
aurelian/agents/checklist/__init__.py
aurelian/agents/checklist/checklist_agent.py
aurelian/agents/checklist/checklist_config.py
aurelian/agents/checklist/checklist_gradio.py
aurelian/agents/checklist/checklist_mcp.py
aurelian/agents/checklist/checklist_tools.py
aurelian/agents/checklist/content/checklists.yaml
aurelian/agents/checklist/content/streams.csv
aurelian/agents/checklist_agent.py
aurelian/agents/chemistry/__init__.py
aurelian/agents/chemistry/chemistry_agent.py
aurelian/agents/chemistry/chemistry_config.py
aurelian/agents/chemistry/chemistry_evals.py
aurelian/agents/chemistry/chemistry_gradio.py
aurelian/agents/chemistry/chemistry_mcp.py
aurelian/agents/chemistry/chemistry_tools.py
aurelian/agents/chemistry/image_agent.py
aurelian/agents/d4d/__init__.py
aurelian/agents/d4d/d4d_agent.py
aurelian/agents/d4d/d4d_config.py
aurelian/agents/d4d/d4d_gradio.py
aurelian/agents/d4d/d4d_mcp.py
aurelian/agents/d4d/d4d_tools.py
aurelian/agents/d4d_agent.py
aurelian/agents/diagnosis/__init__.py
aurelian/agents/diagnosis/diagnosis_agent.py
aurelian/agents/diagnosis/diagnosis_config.py
aurelian/agents/diagnosis/diagnosis_evals.py
aurelian/agents/diagnosis/diagnosis_gradio.py
aurelian/agents/diagnosis/diagnosis_mcp.py
aurelian/agents/diagnosis/diagnosis_tools.py
aurelian/agents/diagnosis_agent.py
aurelian/agents/draw/__init__.py
aurelian/agents/draw/draw_agent.py
aurelian/agents/draw/draw_config.py
aurelian-0.4.2.dist-info/LICENSE
aurelian-0.4.2.dist-info/METADATA
aurelian-0.4.2.dist-info/WHEEL
aurelian-0.4.2.dist-info/entry_points.txt
aurelian-0.4.2.dist-info/RECORD
