Metadata-Version: 2.3
Name: aurelian
Version: 0.4.2
Summary: aurelian
License: MIT
Author: Author 1
Author-email: author@org.org
Requires-Python: >=3.11,<4.0
Classifier: License :: OSI Approved :: MIT License
Classifier: Programming Language :: Python :: 3
Classifier: Programming Language :: Python :: 3.11
Classifier: Programming Language :: Python :: 3.12
Classifier: Programming Language :: Python :: 3.13
Provides-Extra: bioservices
Provides-Extra: chem
Provides-Extra: gocam
Provides-Extra: gradio
Provides-Extra: linkml
Provides-Extra: pdfminer
Provides-Extra: pypaperbot
Provides-Extra: rdkit
Requires-Dist: bioservices (>=1.12.0) ; extra == "bioservices"
Requires-Dist: bs4 (>=0.0.2)
Requires-Dist: cairosvg (>=2.7.1,<3.0.0)
Requires-Dist: click
Requires-Dist: duckduckgo-search (>=7.3.2)
Requires-Dist: gocam ; extra == "gocam"
Requires-Dist: gradio (>=5.23.3,<6.0.0) ; extra == "gradio"
Requires-Dist: importlib-metadata (>=8.2.0)
Requires-Dist: linkml ; extra == "linkml"
Requires-Dist: linkml-store[llm,mongodb] (>=0.2.4)
Requires-Dist: logfire (>=3.5.3)
Requires-Dist: markdownify (>=0.14.1)
Requires-Dist: markitdown (>=0.1.1)
Requires-Dist: mcp[cli] (>=1.3.0,<2.0.0)
Requires-Dist: oaklib (>=0.6.19)
Requires-Dist: onnxruntime (<=1.19.0)
Requires-Dist: paper-qa (>=5.20.0,<6.0.0)
Requires-Dist: pdfminer-six ; extra == "pdfminer"
Requires-Dist: pydantic-ai (>=0.2.0)
Requires-Dist: pypaperbot (>=1.4.1) ; extra == "pypaperbot"
Requires-Dist: pytest-asyncio (>=0.25.3,<0.26.0)
Requires-Dist: rdkit ; extra == "rdkit" or extra == "chem"
Requires-Dist: tabulate (>=0.9.0)
Requires-Dist: undetected-chromedriver (>=3.5.5)
Requires-Dist: wikipedia (>=1.4.0)
